datime/__init__.py
datime-2026.0.dist-info/WHEEL
datime-2026.0.dist-info/METADATA
datime-2026.0.dist-info/RECORD
