Metadata-Version: 2.4
Name: datime
Version: 2026.0
Summary: Python package with convenience functions for dates, times, and intervals
Author: William Jackson
Author-email: William Jackson <william@subtlecoolness.com>
License-Expression: MIT
Classifier: Programming Language :: Python :: 3
Classifier: Operating System :: OS Independent
Requires-Python: >=3.10
Project-URL: Changes, https://github.com/williamjacksn/datime/blob/main/CHANGES.md
Project-URL: Homepage, https://github.com/williamjacksn/datime
Project-URL: Issues, https://github.com/williamjacksn/datime/issues
